{
  "project_info": {
    "project_number": "427044302602",
    "firebase_url": "https://blockchain-e330b.firebaseio.com",
    "project_id": "blockchain-e330b",
    "storage_bucket": "blockchain-e330b.appspot.com"
  },
  "client": [
    {
      "client_info": {
        "mobilesdk_app_id": "1:427044302602:android:33450afb804ec56e",
        "android_client_info": {
          "package_name": "com.plarent.blockchain"
        }
      },
      "oauth_client": [
        {
          "client_id": "427044302602-3uceb9gu4tcfta9jbq1hor3nku91v7n5.apps.googleusercontent.com",
          "client_type": 1,
          "android_info": {
            "package_name": "com.plarent.blockchain",
            "certificate_hash": "765975c7b4ba34b6ed2af7838fa1e18ebbda6876"
          }
        },
        {
          "client_id": "427044302602-61aqmqj7v785035tjufd3bngu1sos7o9.apps.googleusercontent.com",
          "client_type": 1,
          "android_info": {
            "package_name": "com.plarent.blockchain",
            "certificate_hash": "1dfc75657d3c5d707ad22924422e8e9bbbeaf9a1"
          }
        },
        {
          "client_id": "427044302602-fp8env2mhtsvt3uai0istlptb8fckjh4.apps.googleusercontent.com",
          "client_type": 1,
          "android_info": {
            "package_name": "com.plarent.blockchain",
            "certificate_hash": "3a280dc503e2d6275f744e6a222893a57156bd14"
          }
        },
        {
          "client_id": "427044302602-b1pqqac4mcj1gescjo0gprghm1dod5k2.apps.googleusercontent.com",
          "client_type": 3
        }
      ],
      "api_key": [
        {
          "current_key": "AIzaSyADnNYCTBZLrauNXFZ7rNBnGMdYb9kravM"
        }
      ],
      "services": {
        "analytics_service": {
          "status": 1
        },
        "appinvite_service": {
          "status": 2,
          "other_platform_oauth_client": [
            {
              "client_id": "427044302602-b1pqqac4mcj1gescjo0gprghm1dod5k2.apps.googleusercontent.com",
              "client_type": 3
            }
          ]
        },
        "ads_service": {
          "status": 2
        }
      }
    }
  ],
  "configuration_version": "1"
}